modsdkspring/__init__.py
modsdkspring/constants.py
modsdkspring/main.py
modsdkspring/plugins/__init__.txt
modsdkspring/plugins/MODSDKSpring/__init__.txt
modsdkspring/plugins/MODSDKSpring/Network/NotifyManage.txt
modsdkspring/plugins/MODSDKSpring/Network/NotifySystem.txt
modsdkspring/plugins/MODSDKSpring/Network/__init__.txt
modsdkspring/plugins/MODSDKSpring/Network/client/NotifyClient.txt
modsdkspring/plugins/MODSDKSpring/Network/client/__init__.txt
modsdkspring/plugins/MODSDKSpring/Network/exception/NetWorkException.txt
modsdkspring/plugins/MODSDKSpring/Network/exception/__init__.txt
modsdkspring/plugins/MODSDKSpring/Network/server/NotifyServer.txt
modsdkspring/plugins/MODSDKSpring/Network/server/__init__.txt
modsdkspring/plugins/MODSDKSpring/core/Autowired.txt
modsdkspring/plugins/MODSDKSpring/core/BeanFactory.txt
modsdkspring/plugins/MODSDKSpring/core/Lazy.txt
modsdkspring/plugins/MODSDKSpring/core/ListenEvent.txt
modsdkspring/plugins/MODSDKSpring/core/SystemInfo.txt
modsdkspring/plugins/MODSDKSpring/core/__init__.txt
modsdkspring/plugins/MODSDKSpring/core/constant/SystemType.txt
modsdkspring/plugins/MODSDKSpring/core/constant/Target.txt
modsdkspring/plugins/MODSDKSpring/core/constant/__init__.txt
modsdkspring/plugins/MODSDKSpring/core/exception/BeanCurrentlyInCreationException.txt
modsdkspring/plugins/MODSDKSpring/core/exception/DecoratorUseException.txt
modsdkspring/plugins/MODSDKSpring/core/exception/__init__.txt
modsdkspring/plugins/MODSDKSpring/core/log/Log.txt
modsdkspring/plugins/MODSDKSpring/core/log/__init__.txt
modsdkspring/template/ClientSystem.txt
modsdkspring/template/ServerSystem.txt
modsdkspring/template/__init__.txt
modsdkspring/template/modMain.txt
modsdkspring/template/components/__init__.txt
modsdkspring/template/components/client/__init__.txt
modsdkspring/template/components/server/__init__.txt
modsdkspring/template/modCommon/__init__.txt
modsdkspring/template/modCommon/modConfig.txt
mc_creatormc_sdkspring-1.2.1.dist-info/LICENSE
mc_creatormc_sdkspring-1.2.1.dist-info/METADATA
mc_creatormc_sdkspring-1.2.1.dist-info/WHEEL
mc_creatormc_sdkspring-1.2.1.dist-info/entry_points.txt
mc_creatormc_sdkspring-1.2.1.dist-info/top_level.txt
mc_creatormc_sdkspring-1.2.1.dist-info/RECORD
