Metadata-Version: 2.1
Name: mc-creatormc-sdkspring
Version: 1.2.1
Summary: 一个基于网易我的世界 MODSDK 开发的框架，可以让开发者更方便的使用 MODSDK。
Home-page: https://github.com/CreatorMC/MODSDKSping
Author: CreatorMC
License: UNKNOWN
Platform: any
Classifier: Programming Language :: Python :: 2.7
Classifier: License :: OSI Approved :: MIT License
